src/__init__.py
src/__main__.py
src/custom_pathlib.py
src/modules.py
src/testa.py
src/utils.py
tsta-0.0.1.6.data/scripts/tsta
tsta-0.0.1.6.dist-info/LICENSE
tsta-0.0.1.6.dist-info/METADATA
tsta-0.0.1.6.dist-info/WHEEL
tsta-0.0.1.6.dist-info/top_level.txt
tsta-0.0.1.6.dist-info/RECORD
