Metadata-Version: 2.1
Name: tsta
Version: 0.0.1.6
Summary: Test your code with comments
Home-page: https://github.com/sanix-darker/testa
Author: Sanix-darker
Author-email: s4nixd@gmail.com
License: UNKNOWN
Platform: UNKNOWN
Classifier: Programming Language :: Python :: 3
Classifier: License :: OSI Approved :: MIT License
Classifier: Operating System :: OS Independent
Requires-Python: >=3.6
